.gitignore
.isort.cfg
.pre-commit-config.yaml
LICENSE.txt
README.md
diyanet.py
pyproject.toml
setup.cfg
setup.py
diyanet.egg-info/PKG-INFO
diyanet.egg-info/SOURCES.txt
diyanet.egg-info/dependency_links.txt
diyanet.egg-info/top_level.txt