Metadata-Version: 2.1
Name: diyanet
Version: 0.1.2
Summary: Diyanet API
Home-page: https://github.com/isidentical/diyanet
Author: isidentical
Author-email: isidentical@gmail.com
License: UNKNOWN
Platform: UNKNOWN
Requires-Python: >=3.7
